RiskChanges/ComputeLoss.py
RiskChanges/ComputeMultiElementRisk.py
RiskChanges/ComputeMultiHazardRisk.py
RiskChanges/ComputeRisk.py
RiskChanges/__init__.py
RiskChanges/__version__.py
RiskChanges/computeExposure.py
RiskChanges/defineEAR.py
RiskChanges/defineHaz.py
RiskChanges/getExposure.py
RiskChanges/getGeoJSON.py
RiskChanges/getLoss.py
RiskChanges/load_DB.py
RiskChanges/load_SHP.py
RiskChanges/load_WCS.py
RiskChanges/load_WFS.py
RiskChanges/load_vuln.py
RiskChanges/standardizeHaz.py
RiskChanges/DataManage/__init__.py
RiskChanges/DataManage/load_SHP.py
RiskChanges/DataManage/load_WCS.py
RiskChanges/DataManage/load_WFS.py
RiskChanges/RiskChangesOps/AggregateData.py
RiskChanges/RiskChangesOps/Test_python.py
RiskChanges/RiskChangesOps/__init__.py
RiskChanges/RiskChangesOps/rasterops.py
RiskChanges/RiskChangesOps/readmeta.py
RiskChanges/RiskChangesOps/readraster.py
RiskChanges/RiskChangesOps/readvector.py
RiskChanges/RiskChangesOps/readvulnerability.py
RiskChanges/RiskChangesOps/vectorops.py
RiskChanges/RiskChangesOps/vulnops.py
RiskChanges/RiskChangesOps/writemeta.py
RiskChanges/RiskChangesOps/writeraster.py
RiskChanges/RiskChangesOps/writevector.py
RiskChanges-2.1.2.dist-info/LICENSE.txt
RiskChanges-2.1.2.dist-info/METADATA
RiskChanges-2.1.2.dist-info/WHEEL
RiskChanges-2.1.2.dist-info/top_level.txt
RiskChanges-2.1.2.dist-info/RECORD
